{
  "unversionedId": "use-interval",
  "id": "version-v3.6.0/use-interval",
  "isDocsHomePage": false,
  "title": "use-interval",
  "description": "@rooks/use-interval",
  "source": "@site/versioned_docs/version-v3.6.0/use-interval.md",
  "slug": "/use-interval",
  "permalink": "/docs/v3.6.0/use-interval",
  "version": "v3.6.0",
  "lastUpdatedBy": "Author",
  "lastUpdatedAt": 1539502055,
  "sidebar_label": "use-interval",
  "sidebar": "version-v3.6.0/docs",
  "previous": {
    "title": "use-intersection-observer-ref",
    "permalink": "/docs/v3.6.0/use-intersection-observer-ref"
  },
  "next": {
    "title": "use-isomorphic-effect",
    "permalink": "/docs/v3.6.0/use-isomorphic-effect"
  }
}